{
  "name": "Md Nafiur Rahman",
  "position": "Chair",
  "memberId": "97454566",
  "recruitmentSession": "2025 - 2026",
  "image": "https://ieeensusb.org/media_files/user_profile_pictures/97454566_profile_picture.jpg",
  "facebook": "#",
  "linkedin": "#",
  "achievements": [
    {
      "title":"Chair Branch",
      "tenure":"2024 - 2025"
    },
    {
      "title":"Vice-Chair (Activity)",
      "tenure":"2023 - 2024"
    }
  ],
  "ieeeMail": "mdnafiur.rahman19@ieee.org",
  "nsuMail": "nafiur.rahman01@northsouth.edu",
  "bloodGroup": "O+",
  "roles": [
    {
      "organization": "IEEE NSU Student Branch",
      "currentPosition": "Chair",
      "team": "Branch",
      "tenure": "2024 - 2025"
    },
    {
      "organization": "IEEE NSU Student Branch",
      "currentPosition": "Vice-Chair (Activity)",
      "team": "Branch",
      "tenure": "2023 - 2024"
    }
  ]
}